atternio/__main__.py
atternio/models/__init__.py
atternio/models/datasearch.py
atternio/models/enumeration.py
atternio/models/preparation.py
atternio/models/validation.py
atternio/tools/__init__.py
atternio/tools/commands.py
atternio/tools/fileoperations.py
atternio/tools/messages.py
atternio-0.2.0.dist-info/METADATA
atternio-0.2.0.dist-info/WHEEL
atternio-0.2.0.dist-info/RECORD
