Metadata-Version: 2.1
Name: atternio
Version: 0.2.0
Summary: A PoC tool for CWE prioritization according to MITRE CAPEC dictionary.
Home-page: https://github.com/seppzer0/atternio
Author: seppzer0
Requires-Python: >=3.9,<4.0
Classifier: Programming Language :: Python :: 3
Classifier: Programming Language :: Python :: 3.9
Classifier: Programming Language :: Python :: 3.10
Classifier: Programming Language :: Python :: 3.11
Requires-Dist: argparse
Requires-Dist: flawfinder
Requires-Dist: tabulate
Project-URL: Repository, https://github.com/seppzer0/atternio
